gempaterkini_chatur/__init__.py
gempaterkini_chatur/example.py
latest_earth_quake_Indonesia_chatur-0.0.6.dist-info/LICENSE
latest_earth_quake_Indonesia_chatur-0.0.6.dist-info/METADATA
latest_earth_quake_Indonesia_chatur-0.0.6.dist-info/WHEEL
latest_earth_quake_Indonesia_chatur-0.0.6.dist-info/top_level.txt
latest_earth_quake_Indonesia_chatur-0.0.6.dist-info/RECORD
